{
  "kind": "collectionType",
  "collectionName": "formularios",
  "info": {
    "singularName": "formulario",
    "pluralName": "formularios",
    "displayName": "formulario"
  },
  "options": {
    "draftAndPublish": false,
    "comment": ""
  },
  "attributes": {
    "name": {
      "type": "string",
      "required": true,
      "minLength": 3
    },
    "email": {
      "type": "string",
      "required": true,
      "unique": true
    },
    "message": {
      "type": "text",
      "required": true,
      "minLength": 10
    }
  }
}